{
	"$schema": "https://schema.management.azure.com/schemas/2015-01-01/deploymentParameters.json#",
	"contentVersion": "1.0.0.0",
	"parameters": {
		"workspaceName": {
			"value": "synapseprodcb199666"
		},
		"datasource_connectionString": {
			"value": ""
		},
		"synapseprodcb199666-WorkspaceDefaultSqlServer_connectionString": {
			"value": "Integrated Security=False;Encrypt=True;Connection Timeout=30;Data Source=tcp:synapseprodcb199666.sql.azuresynapse.net,1433;Initial Catalog=@{linkedService().DBName}"
		},
		"synapseprodcb199666-WorkspaceDefaultStorage_properties_typeProperties_url": {
			"value": "https://cb19996prod6jjl7esczhw56.dfs.core.windows.net"
		}
	}
}